easyLite/EasyLiteBuild.py
easyLite/EasyLiteCore.py
easyLite/EasyLiteQuery.py
easyLite/EasyLiteRecord.py
easyLite/EasyLiteResult.py
easyLite/__init__.py
easyLite-1.7.1.dist-info/LICENSE
easyLite-1.7.1.dist-info/METADATA
easyLite-1.7.1.dist-info/WHEEL
easyLite-1.7.1.dist-info/top_level.txt
easyLite-1.7.1.dist-info/RECORD
