Metadata-Version: 2.2
Name: easyLite
Version: 1.7.1
Summary: A fluent and user-friendly SQLite library
Home-page: https://github.com/eaannist/easyLite
Author: eaannist
Author-email: eaannist@gmail.com
Classifier: Programming Language :: Python :: 3
Classifier: License :: OSI Approved :: MIT License
Classifier: Operating System :: OS Independent
Requires-Python: >=3.7
License-File: LICENSE
Dynamic: author
Dynamic: author-email
Dynamic: classifier
Dynamic: description
Dynamic: description-content-type
Dynamic: home-page
Dynamic: requires-python
Dynamic: summary
